wphooks/__init__.py
wphooks/wp_actions.py
wphooks/wp_filters.py
wphooks-0.1.0.dist-info/licenses/LICENSE
wphooks-0.1.0.dist-info/METADATA
wphooks-0.1.0.dist-info/WHEEL
wphooks-0.1.0.dist-info/top_level.txt
wphooks-0.1.0.dist-info/RECORD
