Metadata-Version: 2.4
Name: wphooks
Version: 0.1.0
Summary: WordPress-style Hooks for Python
Home-page: https://github.com/manuelcanga/wphooks
Author: Manuel Canga
Classifier: Programming Language :: Python :: 3
Classifier: License :: OSI Approved :: MIT License
Classifier: Operating System :: OS Independent
Requires-Python: >=3.6
License-File: LICENSE
Dynamic: author
Dynamic: classifier
Dynamic: description
Dynamic: description-content-type
Dynamic: home-page
Dynamic: license-file
Dynamic: requires-python
Dynamic: summary
